Workbook

Sheet START HERE
A1: ✅ Signing Agent HQ
A2: The complete notary business & tax system — start here.
A4: 1. | B4: In Google Sheets: File → Make a copy. In Excel: just save your own copy.
A5: 2. | B5: Open the Settings tab and enter this year's IRS standard mileage rate.
A6: 3. | B6: Add your title/escrow companies in the Companies tab.
A7: 4. | B7: Log each job in the Signing Log — Net profit calculates itself.
A8: 5. | B8: Log drives in the Mileage Log and costs in Expenses as you go.
A9: 6. | B9: Watch the Dashboard. At tax time, hand the Tax Summary to your accountant.
A11: Tabs: Settings · Companies · Signing Log · Mileage Log · Expenses · Invoice · Tax Summary · Dashboard
A13: ⚠️ Disclaimer: this is an organizer, not legal or tax advice. Confirm all figures with a professional.
A15: © Signing Agent HQ — single-user license. Do not redistribute.

Sheet Settings
A1: ⚙️ Settings
A2: Update once a year. Everything else flows from here.
E3: Appt types | F3: Status | G3: Expense categories
A4: IRS standard mileage rate (this year) | B4: 0.7 | C4: ← enter the official IRS rate for the current tax year | E4: Refi | F4: Scheduled | G4: Mileage
E5: Purchase | F5: Completed | G5: Supplies
A6: Business name | B6: Your Notary Business, LLC | E6: Seller | F6: Docs back | G6: E&O Insurance
A7: Your name | B7: Your Name | E7: HELOC | F7: Invoiced | G7: Training/Education
E8: Reverse | F8: Paid | G8: Phone/Internet
E9: Apostille | F9: Cancelled | G9: NNA Membership
E10: RON | G10: Software
E11: Inspection | G11: Marketing
E12: General Notary | G12: Printing
G13: Other

Sheet Companies
A1: 🏢 Title / Escrow Companies
A2: Rate who pays best and fastest — fire the slow payers.
A4: Company | B4: Contact | C4: Phone / Email | D4: Avg fee | E4: Pay speed (days) | F4: Rating ★ (1-5) | G4: Notes
A5: Summit Title | B5: Dana R. | C5: dana@summit.com | D5: 125 | E5: 14 | F5: 5 | G5: Reliable, books weekly
A6: BlueRock Escrow | B6: Marcus | C6: ops@bluerock.com | D6: 100 | E6: 30 | F6: 3 | G6: Slow pay, chase invoices
A7: Coastal Signings | B7: Priya | C7: 555-0142 | D7: 150 | E7: 10 | F7: 5 | G7: Best payer — prioritize

Sheet Signing Log
A1: 🖊️ Signing Log + CRM
A2: One row per appointment. Net profit calculates itself.
A4: Date | B4: Company | C4: Order # | D4: Borrower | E4: Appt type | F4: Fee quoted | G4: Fee paid | H4: Status | I4: Miles (round-trip) | J4: Print pages | K4: Other cost | L4: Net profit | M4: Paid?
A5: 2026-01-08 | B5: Coastal Signings | C5: CS-1042 | D5: J. Alvarez | E5: Refi | F5: 150 | G5: 150 | H5: Paid | I5: 24 | J5: 130 | K5: 0 | L5: =IF(G5="","",G5-(I5*Settings!$B$4)-(J5*0.1)-K5) | M5: =IF(H5="Paid","✔","")
A6: 2026-01-11 | B6: Summit Title | C6: ST-9981 | D6: M. Chen | E6: Purchase | F6: 125 | G6: 125 | H6: Paid | I6: 18 | J6: 110 | K6: 0 | L6: =IF(G6="","",G6-(I6*Settings!$B$4)-(J6*0.1)-K6) | M6: =IF(H6="Paid","✔","")
A7: 2026-01-14 | B7: BlueRock Escrow | C7: BR-204 | D7: T. Okafor | E7: HELOC | F7: 100 | G7: 0 | H7: Invoiced | I7: 32 | J7: 60 | K7: 0 | L7: =IF(G7="","",G7-(I7*Settings!$B$4)-(J7*0.1)-K7) | M7: =IF(H7="Paid","✔","")
A8: 2026-01-16 | B8: Coastal Signings | C8: CS-1051 | D8: R. Patel | E8: Seller | F8: 150 | G8: 150 | H8: Paid | I8: 12 | J8: 40 | K8: 0 | L8: =IF(G8="","",G8-(I8*Settings!$B$4)-(J8*0.1)-K8) | M8: =IF(H8="Paid","✔","")
A9: 2026-01-21 | B9: Summit Title | C9: ST-1007 | D9: K. Wallace | E9: Refi | F9: 125 | G9: 0 | H9: Docs back | I9: 27 | J9: 120 | K9: 0 | L9: =IF(G9="","",G9-(I9*Settings!$B$4)-(J9*0.1)-K9) | M9: =IF(H9="Paid","✔","")
L10: =IF(G10="","",G10-(I10*Settings!$B$4)-(J10*0.1)-K10) | M10: =IF(H10="Paid","✔","")
L11: =IF(G11="","",G11-(I11*Settings!$B$4)-(J11*0.1)-K11) | M11: =IF(H11="Paid","✔","")
L12: =IF(G12="","",G12-(I12*Settings!$B$4)-(J12*0.1)-K12) | M12: =IF(H12="Paid","✔","")
L13: =IF(G13="","",G13-(I13*Settings!$B$4)-(J13*0.1)-K13) | M13: =IF(H13="Paid","✔","")
L14: =IF(G14="","",G14-(I14*Settings!$B$4)-(J14*0.1)-K14) | M14: =IF(H14="Paid","✔","")
L15: =IF(G15="","",G15-(I15*Settings!$B$4)-(J15*0.1)-K15) | M15: =IF(H15="Paid","✔","")
L16: =IF(G16="","",G16-(I16*Settings!$B$4)-(J16*0.1)-K16) | M16: =IF(H16="Paid","✔","")
L17: =IF(G17="","",G17-(I17*Settings!$B$4)-(J17*0.1)-K17) | M17: =IF(H17="Paid","✔","")
L18: =IF(G18="","",G18-(I18*Settings!$B$4)-(J18*0.1)-K18) | M18: =IF(H18="Paid","✔","")
L19: =IF(G19="","",G19-(I19*Settings!$B$4)-(J19*0.1)-K19) | M19: =IF(H19="Paid","✔","")
L20: =IF(G20="","",G20-(I20*Settings!$B$4)-(J20*0.1)-K20) | M20: =IF(H20="Paid","✔","")
L21: =IF(G21="","",G21-(I21*Settings!$B$4)-(J21*0.1)-K21) | M21: =IF(H21="Paid","✔","")
... L304: =IF(G304="","",G304-(I304*Settings!$B$4)-(J304*0.1)-K304) | M304: =IF(H304="Paid","✔","")

Sheet Mileage Log
A1: 🚗 IRS Mileage Log
A2: Track every business mile — deduction calculates automatically.
A4: Date | B4: Order # / Purpose | C4: From | D4: To | E4: Round-trip miles | F4: Deduction ($)
A5: 2026-01-08 | B5: CS-1042 signing | C5: Home | D5: Riverside | E5: 24 | F5: =IF(E5="","",E5*Settings!$B$4)
A6: 2026-01-11 | B6: ST-9981 signing | C6: Home | D6: Downtown | E6: 18 | F6: =IF(E6="","",E6*Settings!$B$4)
F7: =IF(E7="","",E7*Settings!$B$4)
F8: =IF(E8="","",E8*Settings!$B$4)
F9: =IF(E9="","",E9*Settings!$B$4)
F10: =IF(E10="","",E10*Settings!$B$4)
F11: =IF(E11="","",E11*Settings!$B$4)
F12: =IF(E12="","",E12*Settings!$B$4)
F13: =IF(E13="","",E13*Settings!$B$4)
F14: =IF(E14="","",E14*Settings!$B$4)
F15: =IF(E15="","",E15*Settings!$B$4)
F16: =IF(E16="","",E16*Settings!$B$4)
F17: =IF(E17="","",E17*Settings!$B$4)
F18: =IF(E18="","",E18*Settings!$B$4)
... F254: =IF(E254="","",E254*Settings!$B$4)

Sheet Expenses
A1: 🧾 Expenses & Supplies
A2: Every deductible dollar, categorized for tax time.
A4: Date | B4: Category | C4: Vendor | D4: Amount | E4: Deductible?
A5: 2026-01-03 | B5: E&O Insurance | C5: NotaryInsure | D5: 75 | E5: Yes
A6: 2026-01-05 | B6: Supplies | C6: Amazon | D6: 38.5 | E6: Yes
A7: 2026-01-09 | B7: Software | C7: Signing Agent HQ | D7: 19 | E7: Yes
A8: 2026-01-10 | B8: Printing | C8: Office Depot | D8: 60 | E8: Yes

Sheet Invoice
A1: 📄 Invoice
A2: Fill the yellow cells, print to PDF, send.
A4: From | D4: Invoice # | E4: INV-0001
A5: =Settings!B6 | D5: Date | E5: 2026-01-31
A6: =Settings!B7
A8: Bill to | B8: Client / Company
A10: Description | B10: Qty | C10: Rate | E10: Amount
A11: Loan signing — Refi | B11: 1 | C11: 150 | E11: =IF(C11="","",B11*C11)
B12: 1 | E12: =IF(C12="","",B12*C12)
B13: 1 | E13: =IF(C13="","",B13*C13)
B14: 1 | E14: =IF(C14="","",B14*C14)
B15: 1 | E15: =IF(C15="","",B15*C15)
B16: 1 | E16: =IF(C16="","",B16*C16)
B17: 1 | E17: =IF(C17="","",B17*C17)
D19: TOTAL | E19: =SUM(E11:E17)

Sheet Tax Summary
A1: 📊 Tax Summary (Schedule C)
A2: Hand this to your accountant. Organizer — not tax advice.
A4: Line item | B4: Schedule C | C4: Amount
A5: Gross income (fees paid) | B5: Part I, Line 1 | C5: =SUMIF('Signing Log'!H5:H304,"Paid",'Signing Log'!G5:G304)
A6: Car / mileage deduction | B6: Line 9 | C6: =SUM('Mileage Log'!F5:F254)
A7: Supplies | B7: Line 22 | C7: =SUMIFS(Expenses!D5:D204,Expenses!B5:B204,"Supplies")
A8: Insurance (E&O) | B8: Line 15 | C8: =SUMIFS(Expenses!D5:D204,Expenses!B5:B204,"E&O Insurance")
A9: Training / education | B9: Line 27a | C9: =SUMIFS(Expenses!D5:D204,Expenses!B5:B204,"Training/Education")
A10: Phone / internet | B10: Line 25 | C10: =SUMIFS(Expenses!D5:D204,Expenses!B5:B204,"Phone/Internet")
A11: Dues / membership (NNA) | B11: Line 27a | C11: =SUMIFS(Expenses!D5:D204,Expenses!B5:B204,"NNA Membership")
A12: Software | B12: Line 27a | C12: =SUMIFS(Expenses!D5:D204,Expenses!B5:B204,"Software")
A13: Marketing / advertising | B13: Line 8 | C13: =SUMIFS(Expenses!D5:D204,Expenses!B5:B204,"Marketing")
A14: Printing | B14: Line 22 | C14: =SUMIFS(Expenses!D5:D204,Expenses!B5:B204,"Printing")
A16: Total expenses | C16: =SUM(C6:C14)
A17: NET PROFIT (est.) | C17: =C5-C16
A19: ⚠️ This is an organizer, not tax advice. Confirm figures with a tax professional.

Sheet Dashboard
A1: 📈 Dashboard
A2: Your business at a glance.
B4: Total fees paid | D4: Outstanding (unpaid) | F4: Net profit (YTD)
B5: =SUMIF('Signing Log'!H5:H304,"Paid",'Signing Log'!G5:G304) | D5: =SUMIF('Signing Log'!H5:H304,"Invoiced",'Signing Log'!F5:F304) | F5: =SUM('Signing Log'!L5:L304)
B7: Signings completed | D7: Total miles (YTD) | F7: Mileage deduction
B8: =COUNTIF('Signing Log'!H5:H304,"Paid")+COUNTIF('Signing Log'!H5:H304,"Invoiced")+COUNTIF('Signing Log'!H5:H304,"Completed") | D8: =SUM('Mileage Log'!E5:E254) | F8: =SUM('Mileage Log'!F5:F254)
B11: Annual income goal | D11: 40000
B12: Progress to goal | D12: =IF(D11=0,0,SUM('Signing Log'!L5:L304)/D11)
B15: Net profit by appointment type
A16: Appt type | B16: Net profit
A17: Refi | B17: =SUMIF('Signing Log'!E5:E304,A17,'Signing Log'!L5:L304)
A18: Purchase | B18: =SUMIF('Signing Log'!E5:E304,A18,'Signing Log'!L5:L304)
A19: Seller | B19: =SUMIF('Signing Log'!E5:E304,A19,'Signing Log'!L5:L304)
A20: HELOC | B20: =SUMIF('Signing Log'!E5:E304,A20,'Signing Log'!L5:L304)
A21: Apostille | B21: =SUMIF('Signing Log'!E5:E304,A21,'Signing Log'!L5:L304)
A22: RON | B22: =SUMIF('Signing Log'!E5:E304,A22,'Signing Log'!L5:L304)
A23: General Notary | B23: =SUMIF('Signing Log'!E5:E304,A23,'Signing Log'!L5:L304)
B26: Cash status
A27: Bucket | B27: Amount
A28: Paid | B28: =SUMIF('Signing Log'!H5:H304,"Paid",'Signing Log'!G5:G304)
A29: Outstanding | B29: =SUMIF('Signing Log'!H5:H304,"Invoiced",'Signing Log'!F5:F304)
